django_json_404_middleware/__init__.py
django_json_404_middleware/middleware.py
django_json_404_middleware-0.0.1.dist-info/DESCRIPTION.rst
django_json_404_middleware-0.0.1.dist-info/METADATA
django_json_404_middleware-0.0.1.dist-info/RECORD
django_json_404_middleware-0.0.1.dist-info/WHEEL
django_json_404_middleware-0.0.1.dist-info/metadata.json
django_json_404_middleware-0.0.1.dist-info/top_level.txt
