Metadata-Version: 2.0
Name: django-json-404-middleware
Version: 0.0.1
Summary: Django middleware that returns 404s as JSON instead of html
Home-page: https://github.com/ah450/django-json-404-middleware
Author: Ahmed Hisham Ismail
Author-email: ahm3d.hisham@gmail.com
License: MIT
Platform: UNKNOWN
Classifier: Environment :: Web Environment
Classifier: Framework :: Django
Classifier: Framework :: Django :: 1.10
Classifier: Intended Audience :: Developers
Classifier: Programming Language :: Python
Classifier: Programming Language :: Python :: 3
Classifier: Topic :: Internet :: WWW/HTTP
Classifier: License :: OSI Approved :: MIT License
